{
  "bg": 109, 
  "temp": "absolute", 
  "snoozeBG": 57, 
  "timestamp": "2016-07-30T07:56:33.253803", 
  "missing": [
    "duration", 
    "rate"
  ], 
  "reason": "Eventual BG 57<130, setting -2.97U/hr, but 27m left and 0 ~ req 0U/hr: no action required", 
  "eventualBG": 57, 
  "error": "missing required input fields", 
  "input": {
    "reason": "Eventual BG 57<130, setting -2.97U/hr, but 27m left and 0 ~ req 0U/hr: no action required", 
    "bg": 109, 
    "eventualBG": 57, 
    "temp": "absolute", 
    "snoozeBG": 57, 
    "mealAssist": "Off: Carbs: undefined Boluses: undefined ISF: 80, Target: 130 Deviation: 4 BGI: -0.92", 
    "tick": "+1"
  }, 
  "mealAssist": "Off: Carbs: undefined Boluses: undefined ISF: 80, Target: 130 Deviation: 4 BGI: -0.92", 
  "tick": "+1"
}