{
  "bg": 231, 
  "temp": "absolute", 
  "snoozeBG": 251, 
  "timestamp": "2016-07-19T23:31:01.340129", 
  "missing": [
    "duration", 
    "rate"
  ], 
  "reason": "Eventual BG 251>=130, adj. req. rate:4.0 to maxSafeBasal:2.4, temp 2.375 >~ req 2.4U/hr", 
  "eventualBG": 251, 
  "error": "missing required input fields", 
  "input": {
    "reason": "Eventual BG 251>=130, adj. req. rate:4.0 to maxSafeBasal:2.4, temp 2.375 >~ req 2.4U/hr", 
    "bg": 231, 
    "eventualBG": 251, 
    "temp": "absolute", 
    "snoozeBG": 251, 
    "mealAssist": "Off: Carbs: undefined Boluses: undefined ISF: 80, Target: 125 Deviation: 21 BGI: 0.12", 
    "tick": "+7"
  }, 
  "mealAssist": "Off: Carbs: undefined Boluses: undefined ISF: 80, Target: 125 Deviation: 21 BGI: 0.12", 
  "tick": "+7"
}