{
  "bg": 152, 
  "temp": "absolute", 
  "snoozeBG": 137, 
  "timestamp": "2016-08-05T15:51:44.180665", 
  "missing": [
    "duration", 
    "rate"
  ], 
  "reason": "Eventual BG 137>130 but Avg. Delta -1.33 < Exp. Delta 0, temp 0.8 ~ req 0.8U/hr", 
  "eventualBG": 137, 
  "error": "missing required input fields", 
  "input": {
    "reason": "Eventual BG 137>130 but Avg. Delta -1.33 < Exp. Delta 0, temp 0.8 ~ req 0.8U/hr", 
    "bg": 152, 
    "eventualBG": 137, 
    "temp": "absolute", 
    "snoozeBG": 137, 
    "mealAssist": "Off: Carbs: undefined Boluses: undefined ISF: 80, Target: 130 Deviation: -9 BGI: 0.12", 
    "tick": "+0"
  }, 
  "mealAssist": "Off: Carbs: undefined Boluses: undefined ISF: 80, Target: 130 Deviation: -9 BGI: 0.12", 
  "tick": "+0"
}