{
  "bg": 166, 
  "temp": "absolute", 
  "snoozeBG": 195, 
  "timestamp": "2016-07-15T12:26:02.121847", 
  "missing": [
    "duration", 
    "rate"
  ], 
  "reason": "Eventual BG 195>=130, adj. req. rate:2.5 to maxSafeBasal:2.4, temp 2.375 >~ req 2.4U/hr", 
  "eventualBG": 195, 
  "error": "missing required input fields", 
  "input": {
    "reason": "Eventual BG 195>=130, adj. req. rate:2.5 to maxSafeBasal:2.4, temp 2.375 >~ req 2.4U/hr", 
    "bg": 166, 
    "eventualBG": 195, 
    "temp": "absolute", 
    "snoozeBG": 195, 
    "mealAssist": "Off: Carbs: undefined Boluses: undefined ISF: 80, Target: 125 Deviation: 3 BGI: 0.44", 
    "tick": "+2"
  }, 
  "mealAssist": "Off: Carbs: undefined Boluses: undefined ISF: 80, Target: 125 Deviation: 3 BGI: 0.44", 
  "tick": "+2"
}