[
  {
    "direction": "Flat", 
    "trend": 4, 
    "dateString": "2016-07-29T09:18:44.000Z", 
    "sgv": 200, 
    "device": "share2", 
    "date": 1469783924000, 
    "_id": "579b1f9d0b12fbe73f0c744b", 
    "type": "sgv"
  }, 
  {
    "direction": "Flat", 
    "trend": 4, 
    "dateString": "2016-07-29T09:13:47.000Z", 
    "sgv": 201, 
    "device": "share2", 
    "date": 1469783627000, 
    "_id": "579b1e710b12fbe73f0c7449", 
    "type": "sgv"
  }, 
  {
    "direction": "Flat", 
    "trend": 4, 
    "dateString": "2016-07-29T09:08:44.000Z", 
    "sgv": 201, 
    "device": "share2", 
    "date": 1469783324000, 
    "_id": "579b1d460b12fbe73f0c7448", 
    "type": "sgv"
  }, 
  {
    "direction": "Flat", 
    "trend": 4, 
    "dateString": "2016-07-29T09:03:45.000Z", 
    "sgv": 202, 
    "device": "share2", 
    "date": 1469783025000, 
    "_id": "579b1c190b12fbe73f0c7447", 
    "type": "sgv"
  }, 
  {
    "direction": "Flat", 
    "trend": 4, 
    "dateString": "2016-07-29T08:58:45.000Z", 
    "sgv": 205, 
    "device": "share2", 
    "date": 1469782725000, 
    "_id": "579b1aed0b12fbe73f0c7446", 
    "type": "sgv"
  }, 
  {
    "direction": "Flat", 
    "trend": 4, 
    "dateString": "2016-07-29T08:53:44.000Z", 
    "sgv": 208, 
    "device": "share2", 
    "date": 1469782424000, 
    "_id": "579b19c10b12fbe73f0c7444", 
    "type": "sgv"
  }, 
  {
    "direction": "FortyFiveUp", 
    "trend": 3, 
    "dateString": "2016-07-29T08:48:46.000Z", 
    "sgv": 212, 
    "device": "share2", 
    "date": 1469782126000, 
    "_id": "579b18950b12fbe73f0c7442", 
    "type": "sgv"
  }, 
  {
    "direction": "Flat", 
    "trend": 4, 
    "dateString": "2016-07-29T08:43:45.000Z", 
    "sgv": 196, 
    "device": "share2", 
    "date": 1469781825000, 
    "_id": "579b17690b12fbe73f0c7441", 
    "type": "sgv"
  }, 
  {
    "direction": "Flat", 
    "trend": 4, 
    "dateString": "2016-07-29T08:38:44.000Z", 
    "sgv": 196, 
    "device": "share2", 
    "date": 1469781524000, 
    "_id": "579b163d0b12fbe73f0c743e", 
    "type": "sgv"
  }, 
  {
    "direction": "Flat", 
    "trend": 4, 
    "dateString": "2016-07-29T08:33:46.000Z", 
    "sgv": 195, 
    "device": "share2", 
    "date": 1469781226000, 
    "_id": "579b15110b12fbe73f0c743d", 
    "type": "sgv"
  }, 
  {
    "direction": "Flat", 
    "trend": 4, 
    "dateString": "2016-07-29T08:28:45.000Z", 
    "sgv": 198, 
    "device": "share2", 
    "date": 1469780925000, 
    "_id": "579b13e50b12fbe73f0c743c", 
    "type": "sgv"
  }, 
  {
    "direction": "Flat", 
    "trend": 4, 
    "dateString": "2016-07-29T08:23:45.000Z", 
    "sgv": 200, 
    "device": "share2", 
    "date": 1469780625000, 
    "_id": "579b12b90b12fbe73f0c743b", 
    "type": "sgv"
  }, 
  {
    "direction": "Flat", 
    "trend": 4, 
    "dateString": "2016-07-29T08:18:44.000Z", 
    "sgv": 205, 
    "device": "share2", 
    "date": 1469780324000, 
    "_id": "579b118d0b12fbe73f0c743a", 
    "type": "sgv"
  }, 
  {
    "direction": "Flat", 
    "trend": 4, 
    "dateString": "2016-07-29T08:13:44.000Z", 
    "sgv": 204, 
    "device": "share2", 
    "date": 1469780024000, 
    "_id": "579b10610b12fbe73f0c7439", 
    "type": "sgv"
  }, 
  {
    "direction": "Flat", 
    "trend": 4, 
    "dateString": "2016-07-29T08:08:45.000Z", 
    "sgv": 202, 
    "device": "share2", 
    "date": 1469779725000, 
    "_id": "579b0f350b12fbe73f0c7438", 
    "type": "sgv"
  }, 
  {
    "direction": "Flat", 
    "trend": 4, 
    "dateString": "2016-07-29T08:03:44.000Z", 
    "sgv": 206, 
    "device": "share2", 
    "date": 1469779424000, 
    "_id": "579b0e090b12fbe73f0c7437", 
    "type": "sgv"
  }, 
  {
    "direction": "Flat", 
    "trend": 4, 
    "dateString": "2016-07-29T07:58:44.000Z", 
    "sgv": 209, 
    "device": "share2", 
    "date": 1469779124000, 
    "_id": "579b0cdd0b12fbe73f0c7436", 
    "type": "sgv"
  }, 
  {
    "direction": "Flat", 
    "trend": 4, 
    "dateString": "2016-07-29T07:53:46.000Z", 
    "sgv": 211, 
    "device": "share2", 
    "date": 1469778826000, 
    "_id": "579b0bb20b12fbe73f0c7435", 
    "type": "sgv"
  }, 
  {
    "direction": "Flat", 
    "trend": 4, 
    "dateString": "2016-07-29T07:48:45.000Z", 
    "sgv": 217, 
    "device": "share2", 
    "date": 1469778525000, 
    "_id": "579b0a850b12fbe73f0c7434", 
    "type": "sgv"
  }, 
  {
    "direction": "Flat", 
    "trend": 4, 
    "dateString": "2016-07-29T07:43:44.000Z", 
    "sgv": 215, 
    "device": "share2", 
    "date": 1469778224000, 
    "_id": "579b095a0b12fbe73f0c7432", 
    "type": "sgv"
  }, 
  {
    "direction": "FortyFiveUp", 
    "trend": 3, 
    "dateString": "2016-07-29T07:38:44.000Z", 
    "sgv": 217, 
    "device": "share2", 
    "date": 1469777924000, 
    "_id": "579b082d0b12fbe73f0c7431", 
    "type": "sgv"
  }, 
  {
    "direction": "FortyFiveUp", 
    "trend": 3, 
    "dateString": "2016-07-29T07:33:45.000Z", 
    "sgv": 216, 
    "device": "share2", 
    "date": 1469777625000, 
    "_id": "579b07010b12fbe73f0c7430", 
    "type": "sgv"
  }, 
  {
    "direction": "Flat", 
    "trend": 4, 
    "dateString": "2016-07-29T07:28:44.000Z", 
    "sgv": 208, 
    "device": "share2", 
    "date": 1469777324000, 
    "_id": "579b05d50b12fbe73f0c742b", 
    "type": "sgv"
  }, 
  {
    "direction": "Flat", 
    "trend": 4, 
    "dateString": "2016-07-29T07:23:45.000Z", 
    "sgv": 195, 
    "device": "share2", 
    "date": 1469777025000, 
    "_id": "579b04a90b12fbe73f0c742a", 
    "type": "sgv"
  }, 
  {
    "direction": "Flat", 
    "trend": 4, 
    "dateString": "2016-07-29T07:18:44.000Z", 
    "sgv": 196, 
    "device": "share2", 
    "date": 1469776724000, 
    "_id": "579b037d0b12fbe73f0c7429", 
    "type": "sgv"
  }, 
  {
    "direction": "FortyFiveUp", 
    "trend": 3, 
    "dateString": "2016-07-29T07:13:44.000Z", 
    "sgv": 199, 
    "device": "share2", 
    "date": 1469776424000, 
    "_id": "579b02510b12fbe73f0c7428", 
    "type": "sgv"
  }, 
  {
    "direction": "SingleUp", 
    "trend": 2, 
    "dateString": "2016-07-29T07:08:44.000Z", 
    "sgv": 200, 
    "device": "share2", 
    "date": 1469776124000, 
    "_id": "579b01250b12fbe73f0c7427", 
    "type": "sgv"
  }, 
  {
    "direction": "FortyFiveUp", 
    "trend": 3, 
    "dateString": "2016-07-29T07:03:44.000Z", 
    "sgv": 189, 
    "device": "share2", 
    "date": 1469775824000, 
    "_id": "579afff90b12fbe73f0c7426", 
    "type": "sgv"
  }, 
  {
    "direction": "FortyFiveUp", 
    "trend": 3, 
    "dateString": "2016-07-29T06:58:46.000Z", 
    "sgv": 179, 
    "device": "share2", 
    "date": 1469775526000, 
    "_id": "579afecd0b12fbe73f0c7425", 
    "type": "sgv"
  }, 
  {
    "direction": "FortyFiveUp", 
    "trend": 3, 
    "dateString": "2016-07-29T06:53:44.000Z", 
    "sgv": 171, 
    "device": "share2", 
    "date": 1469775224000, 
    "_id": "579afda10b12fbe73f0c7424", 
    "type": "sgv"
  }, 
  {
    "direction": "Flat", 
    "trend": 4, 
    "dateString": "2016-07-29T06:48:45.000Z", 
    "sgv": 163, 
    "device": "share2", 
    "date": 1469774925000, 
    "_id": "579afc750b12fbe73f0c7423", 
    "type": "sgv"
  }, 
  {
    "direction": "Flat", 
    "trend": 4, 
    "dateString": "2016-07-29T06:43:44.000Z", 
    "sgv": 156, 
    "device": "share2", 
    "date": 1469774624000, 
    "_id": "579afb490b12fbe73f0c7422", 
    "type": "sgv"
  }, 
  {
    "direction": "Flat", 
    "trend": 4, 
    "dateString": "2016-07-29T06:38:45.000Z", 
    "sgv": 153, 
    "device": "share2", 
    "date": 1469774325000, 
    "_id": "579afa1d0b12fbe73f0c7421", 
    "type": "sgv"
  }, 
  {
    "direction": "Flat", 
    "trend": 4, 
    "dateString": "2016-07-29T06:33:45.000Z", 
    "sgv": 153, 
    "device": "share2", 
    "date": 1469774025000, 
    "_id": "579af8f10b12fbe73f0c7420", 
    "type": "sgv"
  }, 
  {
    "direction": "Flat", 
    "trend": 4, 
    "dateString": "2016-07-29T06:28:44.000Z", 
    "sgv": 152, 
    "device": "share2", 
    "date": 1469773724000, 
    "_id": "579af7c50b12fbe73f0c741f", 
    "type": "sgv"
  }, 
  {
    "direction": "Flat", 
    "trend": 4, 
    "dateString": "2016-07-29T06:23:45.000Z", 
    "sgv": 150, 
    "device": "share2", 
    "date": 1469773425000, 
    "_id": "579af6990b12fbe73f0c741d", 
    "type": "sgv"
  }, 
  {
    "direction": "Flat", 
    "trend": 4, 
    "dateString": "2016-07-29T06:18:44.000Z", 
    "sgv": 147, 
    "device": "share2", 
    "date": 1469773124000, 
    "_id": "579af56d0b12fbe73f0c741c", 
    "type": "sgv"
  }, 
  {
    "direction": "Flat", 
    "trend": 4, 
    "dateString": "2016-07-29T06:13:45.000Z", 
    "sgv": 141, 
    "device": "share2", 
    "date": 1469772825000, 
    "_id": "579af4410b12fbe73f0c741b", 
    "type": "sgv"
  }, 
  {
    "direction": "Flat", 
    "trend": 4, 
    "dateString": "2016-07-29T06:08:46.000Z", 
    "sgv": 139, 
    "device": "share2", 
    "date": 1469772526000, 
    "_id": "579af3150b12fbe73f0c7419", 
    "type": "sgv"
  }, 
  {
    "direction": "Flat", 
    "trend": 4, 
    "dateString": "2016-07-29T06:03:45.000Z", 
    "sgv": 140, 
    "device": "share2", 
    "date": 1469772225000, 
    "_id": "579af1e90b12fbe73f0c7418", 
    "type": "sgv"
  }, 
  {
    "direction": "Flat", 
    "trend": 4, 
    "dateString": "2016-07-29T05:58:46.000Z", 
    "sgv": 140, 
    "device": "share2", 
    "date": 1469771926000, 
    "_id": "579af0bd0b12fbe73f0c7417", 
    "type": "sgv"
  }, 
  {
    "direction": "Flat", 
    "trend": 4, 
    "dateString": "2016-07-29T05:53:45.000Z", 
    "sgv": 138, 
    "device": "share2", 
    "date": 1469771625000, 
    "_id": "579aef910b12fbe73f0c7416", 
    "type": "sgv"
  }, 
  {
    "direction": "Flat", 
    "trend": 4, 
    "dateString": "2016-07-29T05:48:45.000Z", 
    "sgv": 132, 
    "device": "share2", 
    "date": 1469771325000, 
    "_id": "579aee650b12fbe73f0c7415", 
    "type": "sgv"
  }, 
  {
    "direction": "Flat", 
    "trend": 4, 
    "dateString": "2016-07-29T05:43:44.000Z", 
    "sgv": 136, 
    "device": "share2", 
    "date": 1469771024000, 
    "_id": "579aed390b12fbe73f0c7414", 
    "type": "sgv"
  }, 
  {
    "direction": "Flat", 
    "trend": 4, 
    "dateString": "2016-07-29T05:38:44.000Z", 
    "sgv": 128, 
    "device": "share2", 
    "date": 1469770724000, 
    "_id": "579aec0d0b12fbe73f0c7412", 
    "type": "sgv"
  }, 
  {
    "direction": "Flat", 
    "trend": 4, 
    "dateString": "2016-07-29T05:33:46.000Z", 
    "sgv": 133, 
    "device": "share2", 
    "date": 1469770426000, 
    "_id": "579aeae10b12fbe73f0c7411", 
    "type": "sgv"
  }, 
  {
    "direction": "Flat", 
    "trend": 4, 
    "dateString": "2016-07-29T05:28:46.000Z", 
    "sgv": 137, 
    "device": "share2", 
    "date": 1469770126000, 
    "_id": "579ae9b50b12fbe73f0c740f", 
    "type": "sgv"
  }, 
  {
    "direction": "Flat", 
    "trend": 4, 
    "dateString": "2016-07-29T05:23:45.000Z", 
    "sgv": 142, 
    "device": "share2", 
    "date": 1469769825000, 
    "_id": "579ae8890b12fbe73f0c740b", 
    "type": "sgv"
  }, 
  {
    "direction": "Flat", 
    "trend": 4, 
    "dateString": "2016-07-29T05:18:46.000Z", 
    "sgv": 140, 
    "device": "share2", 
    "date": 1469769526000, 
    "_id": "579ae75d0b12fbe73f0c740a", 
    "type": "sgv"
  }, 
  {
    "direction": "Flat", 
    "trend": 4, 
    "dateString": "2016-07-29T05:13:46.000Z", 
    "sgv": 138, 
    "device": "share2", 
    "date": 1469769226000, 
    "_id": "579ae6310b12fbe73f0c7408", 
    "type": "sgv"
  }
]