[
  {
    "direction": "Flat", 
    "trend": 4, 
    "dateString": "2016-07-20T10:29:07.000Z", 
    "sgv": 219, 
    "device": "share2", 
    "date": 1469010547000, 
    "_id": "578f52750b12fbe73f0c4ce3", 
    "type": "sgv"
  }, 
  {
    "direction": "Flat", 
    "trend": 4, 
    "dateString": "2016-07-20T10:24:07.000Z", 
    "sgv": 221, 
    "device": "share2", 
    "date": 1469010247000, 
    "_id": "578f51490b12fbe73f0c4ce1", 
    "type": "sgv"
  }, 
  {
    "direction": "Flat", 
    "trend": 4, 
    "dateString": "2016-07-20T10:19:08.000Z", 
    "sgv": 218, 
    "device": "share2", 
    "date": 1469009948000, 
    "_id": "578f50b30b12fbe73f0c4ce0", 
    "type": "sgv"
  }, 
  {
    "direction": "Flat", 
    "trend": 4, 
    "dateString": "2016-07-20T10:14:08.000Z", 
    "sgv": 211, 
    "device": "share2", 
    "date": 1469009648000, 
    "_id": "578f4f870b12fbe73f0c4cdf", 
    "type": "sgv"
  }, 
  {
    "direction": "Flat", 
    "trend": 4, 
    "dateString": "2016-07-20T10:09:08.000Z", 
    "sgv": 213, 
    "device": "share2", 
    "date": 1469009348000, 
    "_id": "578f4dc50b12fbe73f0c4cdd", 
    "type": "sgv"
  }, 
  {
    "direction": "Flat", 
    "trend": 4, 
    "dateString": "2016-07-20T10:04:07.000Z", 
    "sgv": 216, 
    "device": "share2", 
    "date": 1469009047000, 
    "_id": "578f4c990b12fbe73f0c4cdc", 
    "type": "sgv"
  }, 
  {
    "direction": "Flat", 
    "trend": 4, 
    "dateString": "2016-07-20T09:59:08.000Z", 
    "sgv": 213, 
    "device": "share2", 
    "date": 1469008748000, 
    "_id": "578f4c030b12fbe73f0c4cdb", 
    "type": "sgv"
  }, 
  {
    "direction": "Flat", 
    "trend": 4, 
    "dateString": "2016-07-20T09:54:09.000Z", 
    "sgv": 220, 
    "device": "share2", 
    "date": 1469008449000, 
    "_id": "578f4ad70b12fbe73f0c4cda", 
    "type": "sgv"
  }, 
  {
    "direction": "Flat", 
    "trend": 4, 
    "dateString": "2016-07-20T09:49:08.000Z", 
    "sgv": 223, 
    "device": "share2", 
    "date": 1469008148000, 
    "_id": "578f49ab0b12fbe73f0c4cd8", 
    "type": "sgv"
  }, 
  {
    "direction": "Flat", 
    "trend": 4, 
    "dateString": "2016-07-20T09:44:06.000Z", 
    "sgv": 226, 
    "device": "share2", 
    "date": 1469007846000, 
    "_id": "578f47e90b12fbe73f0c4cd7", 
    "type": "sgv"
  }, 
  {
    "direction": "Flat", 
    "trend": 4, 
    "dateString": "2016-07-20T09:39:08.000Z", 
    "sgv": 229, 
    "device": "share2", 
    "date": 1469007548000, 
    "_id": "578f47530b12fbe73f0c4cd6", 
    "type": "sgv"
  }, 
  {
    "direction": "Flat", 
    "trend": 4, 
    "dateString": "2016-07-20T09:34:10.000Z", 
    "sgv": 233, 
    "device": "share2", 
    "date": 1469007250000, 
    "_id": "578f46270b12fbe73f0c4cd5", 
    "type": "sgv"
  }, 
  {
    "direction": "Flat", 
    "trend": 4, 
    "dateString": "2016-07-20T09:29:06.000Z", 
    "sgv": 238, 
    "device": "share2", 
    "date": 1469006946000, 
    "_id": "578f44650b12fbe73f0c4cd3", 
    "type": "sgv"
  }, 
  {
    "direction": "Flat", 
    "trend": 4, 
    "dateString": "2016-07-20T09:24:10.000Z", 
    "sgv": 241, 
    "device": "share2", 
    "date": 1469006650000, 
    "_id": "578f43cf0b12fbe73f0c4cd2", 
    "type": "sgv"
  }, 
  {
    "direction": "Flat", 
    "trend": 4, 
    "dateString": "2016-07-20T09:19:08.000Z", 
    "sgv": 244, 
    "device": "share2", 
    "date": 1469006348000, 
    "_id": "578f42a30b12fbe73f0c4cd1", 
    "type": "sgv"
  }, 
  {
    "direction": "Flat", 
    "trend": 4, 
    "dateString": "2016-07-20T09:14:06.000Z", 
    "sgv": 244, 
    "device": "share2", 
    "date": 1469006046000, 
    "_id": "578f40e10b12fbe73f0c4ccf", 
    "type": "sgv"
  }, 
  {
    "direction": "Flat", 
    "trend": 4, 
    "dateString": "2016-07-20T09:09:08.000Z", 
    "sgv": 241, 
    "device": "share2", 
    "date": 1469005748000, 
    "_id": "578f404b0b12fbe73f0c4cce", 
    "type": "sgv"
  }, 
  {
    "direction": "Flat", 
    "trend": 4, 
    "dateString": "2016-07-20T09:04:08.000Z", 
    "sgv": 238, 
    "device": "share2", 
    "date": 1469005448000, 
    "_id": "578f3f1f0b12fbe73f0c4ccd", 
    "type": "sgv"
  }, 
  {
    "direction": "FortyFiveUp", 
    "trend": 3, 
    "dateString": "2016-07-20T08:59:06.000Z", 
    "sgv": 237, 
    "device": "share2", 
    "date": 1469005146000, 
    "_id": "578f3d5d0b12fbe73f0c4ccc", 
    "type": "sgv"
  }, 
  {
    "direction": "FortyFiveUp", 
    "trend": 3, 
    "dateString": "2016-07-20T08:54:06.000Z", 
    "sgv": 234, 
    "device": "share2", 
    "date": 1469004846000, 
    "_id": "578f3c310b12fbe73f0c4ccb", 
    "type": "sgv"
  }, 
  {
    "direction": "FortyFiveUp", 
    "trend": 3, 
    "dateString": "2016-07-20T08:49:08.000Z", 
    "sgv": 231, 
    "device": "share2", 
    "date": 1469004548000, 
    "_id": "578f3b9b0b12fbe73f0c4cca", 
    "type": "sgv"
  }, 
  {
    "direction": "Flat", 
    "trend": 4, 
    "dateString": "2016-07-20T08:44:07.000Z", 
    "sgv": 224, 
    "device": "share2", 
    "date": 1469004247000, 
    "_id": "578f39d90b12fbe73f0c4cc8", 
    "type": "sgv"
  }, 
  {
    "direction": "Flat", 
    "trend": 4, 
    "dateString": "2016-07-20T08:39:06.000Z", 
    "sgv": 211, 
    "device": "share2", 
    "date": 1469003946000, 
    "_id": "578f38ad0b12fbe73f0c4cc7", 
    "type": "sgv"
  }, 
  {
    "direction": "FortyFiveDown", 
    "trend": 5, 
    "dateString": "2016-07-20T08:34:15.000Z", 
    "sgv": 212, 
    "device": "share2", 
    "date": 1469003655000, 
    "_id": "578f38170b12fbe73f0c4cc6", 
    "type": "sgv"
  }, 
  {
    "direction": "Flat", 
    "trend": 4, 
    "dateString": "2016-07-20T08:29:08.000Z", 
    "sgv": 217, 
    "device": "share2", 
    "date": 1469003348000, 
    "_id": "578f36eb0b12fbe73f0c4cc5", 
    "type": "sgv"
  }, 
  {
    "direction": "Flat", 
    "trend": 4, 
    "dateString": "2016-07-20T08:24:07.000Z", 
    "sgv": 223, 
    "device": "share2", 
    "date": 1469003047000, 
    "_id": "578f35290b12fbe73f0c4cc3", 
    "type": "sgv"
  }, 
  {
    "direction": "Flat", 
    "trend": 4, 
    "dateString": "2016-07-20T08:19:13.000Z", 
    "sgv": 233, 
    "device": "share2", 
    "date": 1469002753000, 
    "_id": "578f34930b12fbe73f0c4cc2", 
    "type": "sgv"
  }, 
  {
    "direction": "Flat", 
    "trend": 4, 
    "dateString": "2016-07-20T08:14:06.000Z", 
    "sgv": 229, 
    "device": "share2", 
    "date": 1469002446000, 
    "_id": "578f33670b12fbe73f0c4cc1", 
    "type": "sgv"
  }, 
  {
    "direction": "Flat", 
    "trend": 4, 
    "dateString": "2016-07-20T08:09:07.000Z", 
    "sgv": 222, 
    "device": "share2", 
    "date": 1469002147000, 
    "_id": "578f31a50b12fbe73f0c4cbf", 
    "type": "sgv"
  }, 
  {
    "direction": "Flat", 
    "trend": 4, 
    "dateString": "2016-07-20T08:04:06.000Z", 
    "sgv": 218, 
    "device": "share2", 
    "date": 1469001846000, 
    "_id": "578f30790b12fbe73f0c4cbd", 
    "type": "sgv"
  }, 
  {
    "direction": "Flat", 
    "trend": 4, 
    "dateString": "2016-07-20T07:59:08.000Z", 
    "sgv": 219, 
    "device": "share2", 
    "date": 1469001548000, 
    "_id": "578f2fe30b12fbe73f0c4cbc", 
    "type": "sgv"
  }, 
  {
    "direction": "Flat", 
    "trend": 4, 
    "dateString": "2016-07-20T07:54:11.000Z", 
    "sgv": 219, 
    "device": "share2", 
    "date": 1469001251000, 
    "_id": "578f2eb70b12fbe73f0c4cba", 
    "type": "sgv"
  }, 
  {
    "direction": "Flat", 
    "trend": 4, 
    "dateString": "2016-07-20T07:49:13.000Z", 
    "sgv": 217, 
    "device": "share2", 
    "date": 1469000953000, 
    "_id": "578f2d8b0b12fbe73f0c4cb7", 
    "type": "sgv"
  }, 
  {
    "direction": "Flat", 
    "trend": 4, 
    "dateString": "2016-07-20T07:44:13.000Z", 
    "sgv": 216, 
    "device": "share2", 
    "date": 1469000653000, 
    "_id": "578f2c5f0b12fbe73f0c4cb6", 
    "type": "sgv"
  }, 
  {
    "direction": "Flat", 
    "trend": 4, 
    "dateString": "2016-07-20T07:39:13.000Z", 
    "sgv": 215, 
    "device": "share2", 
    "date": 1469000353000, 
    "_id": "578f2b330b12fbe73f0c4cb4", 
    "type": "sgv"
  }, 
  {
    "direction": "Flat", 
    "trend": 4, 
    "dateString": "2016-07-20T07:34:07.000Z", 
    "sgv": 216, 
    "device": "share2", 
    "date": 1469000047000, 
    "_id": "578f29710b12fbe73f0c4cb2", 
    "type": "sgv"
  }, 
  {
    "direction": "Flat", 
    "trend": 4, 
    "dateString": "2016-07-20T07:29:19.000Z", 
    "sgv": 217, 
    "device": "share2", 
    "date": 1468999759000, 
    "_id": "578f28db0b12fbe73f0c4cb1", 
    "type": "sgv"
  }, 
  {
    "direction": "Flat", 
    "trend": 4, 
    "dateString": "2016-07-20T07:24:08.000Z", 
    "sgv": 216, 
    "device": "share2", 
    "date": 1468999448000, 
    "_id": "578f27af0b12fbe73f0c4cb0", 
    "type": "sgv"
  }, 
  {
    "direction": "Flat", 
    "trend": 4, 
    "dateString": "2016-07-20T07:19:12.000Z", 
    "sgv": 216, 
    "device": "share2", 
    "date": 1468999152000, 
    "_id": "578f26830b12fbe73f0c4cad", 
    "type": "sgv"
  }, 
  {
    "direction": "Flat", 
    "trend": 4, 
    "dateString": "2016-07-20T07:09:09.000Z", 
    "sgv": 213, 
    "device": "share2", 
    "date": 1468998549000, 
    "_id": "578f242b0b12fbe73f0c4cab", 
    "type": "sgv"
  }, 
  {
    "direction": "Flat", 
    "trend": 4, 
    "dateString": "2016-07-20T07:04:07.000Z", 
    "sgv": 213, 
    "device": "share2", 
    "date": 1468998247000, 
    "_id": "578f22690b12fbe73f0c4ca9", 
    "type": "sgv"
  }, 
  {
    "direction": "Flat", 
    "trend": 4, 
    "dateString": "2016-07-20T06:59:18.000Z", 
    "sgv": 213, 
    "device": "share2", 
    "date": 1468997958000, 
    "_id": "578f21d30b12fbe73f0c4ca8", 
    "type": "sgv"
  }, 
  {
    "direction": "FortyFiveDown", 
    "trend": 5, 
    "dateString": "2016-07-20T06:54:05.000Z", 
    "sgv": 214, 
    "device": "share2", 
    "date": 1468997645000, 
    "_id": "578f20110b12fbe73f0c4ca6", 
    "type": "sgv"
  }, 
  {
    "direction": "Flat", 
    "trend": 4, 
    "dateString": "2016-07-20T06:49:09.000Z", 
    "sgv": 220, 
    "device": "share2", 
    "date": 1468997349000, 
    "_id": "578f1f7b0b12fbe73f0c4ca4", 
    "type": "sgv"
  }, 
  {
    "direction": "Flat", 
    "trend": 4, 
    "dateString": "2016-07-20T06:44:10.000Z", 
    "sgv": 228, 
    "device": "share2", 
    "date": 1468997050000, 
    "_id": "578f1e4f0b12fbe73f0c4ca3", 
    "type": "sgv"
  }, 
  {
    "direction": "Flat", 
    "trend": 4, 
    "dateString": "2016-07-20T06:39:06.000Z", 
    "sgv": 231, 
    "device": "share2", 
    "date": 1468996746000, 
    "_id": "578f1c8d0b12fbe73f0c4ca2", 
    "type": "sgv"
  }, 
  {
    "direction": "FortyFiveUp", 
    "trend": 3, 
    "dateString": "2016-07-20T06:34:07.000Z", 
    "sgv": 231, 
    "device": "share2", 
    "date": 1468996447000, 
    "_id": "578f1b610b12fbe73f0c4ca1", 
    "type": "sgv"
  }, 
  {
    "direction": "FortyFiveUp", 
    "trend": 3, 
    "dateString": "2016-07-20T06:29:05.000Z", 
    "sgv": 231, 
    "device": "share2", 
    "date": 1468996145000, 
    "_id": "578f1a350b12fbe73f0c4ca0", 
    "type": "sgv"
  }, 
  {
    "direction": "FortyFiveUp", 
    "trend": 3, 
    "dateString": "2016-07-20T06:24:06.000Z", 
    "sgv": 224, 
    "device": "share2", 
    "date": 1468995846000, 
    "_id": "578f19090b12fbe73f0c4c9f", 
    "type": "sgv"
  }, 
  {
    "direction": "Flat", 
    "trend": 4, 
    "dateString": "2016-07-20T06:19:06.000Z", 
    "sgv": 214, 
    "device": "share2", 
    "date": 1468995546000, 
    "_id": "578f17dd0b12fbe73f0c4c9d", 
    "type": "sgv"
  }
]