[
  {
    "direction": "Flat", 
    "trend": 4, 
    "dateString": "2016-08-02T12:58:34.000Z", 
    "sgv": 148, 
    "device": "share2", 
    "date": 1470142714000, 
    "_id": "57a099720b12fbe73f0c7981", 
    "type": "sgv"
  }, 
  {
    "direction": "Flat", 
    "trend": 4, 
    "dateString": "2016-08-02T12:53:35.000Z", 
    "sgv": 149, 
    "device": "share2", 
    "date": 1470142415000, 
    "_id": "57a098460b12fbe73f0c7980", 
    "type": "sgv"
  }, 
  {
    "direction": "Flat", 
    "trend": 4, 
    "dateString": "2016-08-02T12:48:34.000Z", 
    "sgv": 146, 
    "device": "share2", 
    "date": 1470142114000, 
    "_id": "57a0971a0b12fbe73f0c797f", 
    "type": "sgv"
  }, 
  {
    "direction": "Flat", 
    "trend": 4, 
    "dateString": "2016-08-02T12:43:38.000Z", 
    "sgv": 147, 
    "device": "share2", 
    "date": 1470141818000, 
    "_id": "57a095ee0b12fbe73f0c797e", 
    "type": "sgv"
  }, 
  {
    "direction": "Flat", 
    "trend": 4, 
    "dateString": "2016-08-02T12:38:34.000Z", 
    "sgv": 151, 
    "device": "share2", 
    "date": 1470141514000, 
    "_id": "57a094c20b12fbe73f0c797d", 
    "type": "sgv"
  }, 
  {
    "direction": "Flat", 
    "trend": 4, 
    "dateString": "2016-08-02T12:33:34.000Z", 
    "sgv": 153, 
    "device": "share2", 
    "date": 1470141214000, 
    "_id": "57a093960b12fbe73f0c797c", 
    "type": "sgv"
  }, 
  {
    "direction": "Flat", 
    "trend": 4, 
    "dateString": "2016-08-02T12:28:36.000Z", 
    "sgv": 154, 
    "device": "share2", 
    "date": 1470140916000, 
    "_id": "57a0926a0b12fbe73f0c797b", 
    "type": "sgv"
  }, 
  {
    "direction": "Flat", 
    "trend": 4, 
    "dateString": "2016-08-02T12:23:35.000Z", 
    "sgv": 156, 
    "device": "share2", 
    "date": 1470140615000, 
    "_id": "57a0913e0b12fbe73f0c797a", 
    "type": "sgv"
  }, 
  {
    "direction": "Flat", 
    "trend": 4, 
    "dateString": "2016-08-02T12:18:35.000Z", 
    "sgv": 158, 
    "device": "share2", 
    "date": 1470140315000, 
    "_id": "57a090120b12fbe73f0c7979", 
    "type": "sgv"
  }, 
  {
    "direction": "Flat", 
    "trend": 4, 
    "dateString": "2016-08-02T12:13:35.000Z", 
    "sgv": 160, 
    "device": "share2", 
    "date": 1470140015000, 
    "_id": "57a08ee60b12fbe73f0c7978", 
    "type": "sgv"
  }, 
  {
    "direction": "Flat", 
    "trend": 4, 
    "dateString": "2016-08-02T12:08:35.000Z", 
    "sgv": 161, 
    "device": "share2", 
    "date": 1470139715000, 
    "_id": "57a08dba0b12fbe73f0c7977", 
    "type": "sgv"
  }, 
  {
    "direction": "Flat", 
    "trend": 4, 
    "dateString": "2016-08-02T12:03:35.000Z", 
    "sgv": 163, 
    "device": "share2", 
    "date": 1470139415000, 
    "_id": "57a08c8e0b12fbe73f0c7976", 
    "type": "sgv"
  }, 
  {
    "direction": "Flat", 
    "trend": 4, 
    "dateString": "2016-08-02T11:58:36.000Z", 
    "sgv": 165, 
    "device": "share2", 
    "date": 1470139116000, 
    "_id": "57a08b620b12fbe73f0c7975", 
    "type": "sgv"
  }, 
  {
    "direction": "Flat", 
    "trend": 4, 
    "dateString": "2016-08-02T11:53:35.000Z", 
    "sgv": 167, 
    "device": "share2", 
    "date": 1470138815000, 
    "_id": "57a08a360b12fbe73f0c7974", 
    "type": "sgv"
  }, 
  {
    "direction": "Flat", 
    "trend": 4, 
    "dateString": "2016-08-02T11:48:36.000Z", 
    "sgv": 167, 
    "device": "share2", 
    "date": 1470138516000, 
    "_id": "57a0890a0b12fbe73f0c7973", 
    "type": "sgv"
  }, 
  {
    "direction": "Flat", 
    "trend": 4, 
    "dateString": "2016-08-02T11:43:36.000Z", 
    "sgv": 166, 
    "device": "share2", 
    "date": 1470138216000, 
    "_id": "57a087de0b12fbe73f0c7972", 
    "type": "sgv"
  }, 
  {
    "direction": "Flat", 
    "trend": 4, 
    "dateString": "2016-08-02T11:38:35.000Z", 
    "sgv": 169, 
    "device": "share2", 
    "date": 1470137915000, 
    "_id": "57a086b20b12fbe73f0c7971", 
    "type": "sgv"
  }, 
  {
    "direction": "Flat", 
    "trend": 4, 
    "dateString": "2016-08-02T11:33:37.000Z", 
    "sgv": 173, 
    "device": "share2", 
    "date": 1470137617000, 
    "_id": "57a085860b12fbe73f0c7970", 
    "type": "sgv"
  }, 
  {
    "direction": "Flat", 
    "trend": 4, 
    "dateString": "2016-08-02T11:28:35.000Z", 
    "sgv": 174, 
    "device": "share2", 
    "date": 1470137315000, 
    "_id": "57a0845a0b12fbe73f0c796f", 
    "type": "sgv"
  }, 
  {
    "direction": "Flat", 
    "trend": 4, 
    "dateString": "2016-08-02T11:23:35.000Z", 
    "sgv": 173, 
    "device": "share2", 
    "date": 1470137015000, 
    "_id": "57a0832e0b12fbe73f0c796e", 
    "type": "sgv"
  }, 
  {
    "direction": "Flat", 
    "trend": 4, 
    "dateString": "2016-08-02T11:18:36.000Z", 
    "sgv": 174, 
    "device": "share2", 
    "date": 1470136716000, 
    "_id": "57a082020b12fbe73f0c796d", 
    "type": "sgv"
  }, 
  {
    "direction": "Flat", 
    "trend": 4, 
    "dateString": "2016-08-02T11:13:38.000Z", 
    "sgv": 176, 
    "device": "share2", 
    "date": 1470136418000, 
    "_id": "57a080d60b12fbe73f0c796c", 
    "type": "sgv"
  }, 
  {
    "direction": "Flat", 
    "trend": 4, 
    "dateString": "2016-08-02T11:08:36.000Z", 
    "sgv": 182, 
    "device": "share2", 
    "date": 1470136116000, 
    "_id": "57a07faa0b12fbe73f0c796b", 
    "type": "sgv"
  }, 
  {
    "direction": "Flat", 
    "trend": 4, 
    "dateString": "2016-08-02T11:03:35.000Z", 
    "sgv": 183, 
    "device": "share2", 
    "date": 1470135815000, 
    "_id": "57a07e7e0b12fbe73f0c796a", 
    "type": "sgv"
  }, 
  {
    "direction": "Flat", 
    "trend": 4, 
    "dateString": "2016-08-02T10:58:36.000Z", 
    "sgv": 169, 
    "device": "share2", 
    "date": 1470135516000, 
    "_id": "57a07d520b12fbe73f0c7969", 
    "type": "sgv"
  }, 
  {
    "direction": "Flat", 
    "trend": 4, 
    "dateString": "2016-08-02T10:53:36.000Z", 
    "sgv": 174, 
    "device": "share2", 
    "date": 1470135216000, 
    "_id": "57a07c260b12fbe73f0c7968", 
    "type": "sgv"
  }, 
  {
    "direction": "Flat", 
    "trend": 4, 
    "dateString": "2016-08-02T10:48:36.000Z", 
    "sgv": 178, 
    "device": "share2", 
    "date": 1470134916000, 
    "_id": "57a07afa0b12fbe73f0c7967", 
    "type": "sgv"
  }, 
  {
    "direction": "Flat", 
    "trend": 4, 
    "dateString": "2016-08-02T10:43:37.000Z", 
    "sgv": 179, 
    "device": "share2", 
    "date": 1470134617000, 
    "_id": "57a079ce0b12fbe73f0c7966", 
    "type": "sgv"
  }, 
  {
    "direction": "Flat", 
    "trend": 4, 
    "dateString": "2016-08-02T10:38:36.000Z", 
    "sgv": 181, 
    "device": "share2", 
    "date": 1470134316000, 
    "_id": "57a078a20b12fbe73f0c7965", 
    "type": "sgv"
  }, 
  {
    "direction": "Flat", 
    "trend": 4, 
    "dateString": "2016-08-02T10:33:35.000Z", 
    "sgv": 183, 
    "device": "share2", 
    "date": 1470134015000, 
    "_id": "57a077760b12fbe73f0c7964", 
    "type": "sgv"
  }, 
  {
    "direction": "Flat", 
    "trend": 4, 
    "dateString": "2016-08-02T10:28:35.000Z", 
    "sgv": 185, 
    "device": "share2", 
    "date": 1470133715000, 
    "_id": "57a0764a0b12fbe73f0c7963", 
    "type": "sgv"
  }, 
  {
    "direction": "Flat", 
    "trend": 4, 
    "dateString": "2016-08-02T10:23:40.000Z", 
    "sgv": 186, 
    "device": "share2", 
    "date": 1470133420000, 
    "_id": "57a0751e0b12fbe73f0c7962", 
    "type": "sgv"
  }, 
  {
    "direction": "Flat", 
    "trend": 4, 
    "dateString": "2016-08-02T10:18:36.000Z", 
    "sgv": 188, 
    "device": "share2", 
    "date": 1470133116000, 
    "_id": "57a073f20b12fbe73f0c7961", 
    "type": "sgv"
  }, 
  {
    "direction": "Flat", 
    "trend": 4, 
    "dateString": "2016-08-02T10:13:36.000Z", 
    "sgv": 190, 
    "device": "share2", 
    "date": 1470132816000, 
    "_id": "57a072c60b12fbe73f0c7960", 
    "type": "sgv"
  }, 
  {
    "direction": "Flat", 
    "trend": 4, 
    "dateString": "2016-08-02T10:08:36.000Z", 
    "sgv": 194, 
    "device": "share2", 
    "date": 1470132516000, 
    "_id": "57a0719a0b12fbe73f0c795f", 
    "type": "sgv"
  }, 
  {
    "direction": "Flat", 
    "trend": 4, 
    "dateString": "2016-08-02T10:03:35.000Z", 
    "sgv": 197, 
    "device": "share2", 
    "date": 1470132215000, 
    "_id": "57a0706e0b12fbe73f0c795e", 
    "type": "sgv"
  }, 
  {
    "direction": "Flat", 
    "trend": 4, 
    "dateString": "2016-08-02T09:58:35.000Z", 
    "sgv": 200, 
    "device": "share2", 
    "date": 1470131915000, 
    "_id": "57a06f420b12fbe73f0c795d", 
    "type": "sgv"
  }, 
  {
    "direction": "Flat", 
    "trend": 4, 
    "dateString": "2016-08-02T09:53:40.000Z", 
    "sgv": 202, 
    "device": "share2", 
    "date": 1470131620000, 
    "_id": "57a06e160b12fbe73f0c795c", 
    "type": "sgv"
  }, 
  {
    "direction": "Flat", 
    "trend": 4, 
    "dateString": "2016-08-02T09:48:37.000Z", 
    "sgv": 202, 
    "device": "share2", 
    "date": 1470131317000, 
    "_id": "57a06cea0b12fbe73f0c795b", 
    "type": "sgv"
  }, 
  {
    "direction": "Flat", 
    "trend": 4, 
    "dateString": "2016-08-02T09:43:36.000Z", 
    "sgv": 202, 
    "device": "share2", 
    "date": 1470131016000, 
    "_id": "57a06bbe0b12fbe73f0c795a", 
    "type": "sgv"
  }, 
  {
    "direction": "Flat", 
    "trend": 4, 
    "dateString": "2016-08-02T09:38:36.000Z", 
    "sgv": 204, 
    "device": "share2", 
    "date": 1470130716000, 
    "_id": "57a06a920b12fbe73f0c7959", 
    "type": "sgv"
  }, 
  {
    "direction": "Flat", 
    "trend": 4, 
    "dateString": "2016-08-02T09:33:36.000Z", 
    "sgv": 205, 
    "device": "share2", 
    "date": 1470130416000, 
    "_id": "57a069660b12fbe73f0c7958", 
    "type": "sgv"
  }, 
  {
    "direction": "Flat", 
    "trend": 4, 
    "dateString": "2016-08-02T09:28:36.000Z", 
    "sgv": 208, 
    "device": "share2", 
    "date": 1470130116000, 
    "_id": "57a0683a0b12fbe73f0c7957", 
    "type": "sgv"
  }, 
  {
    "direction": "Flat", 
    "trend": 4, 
    "dateString": "2016-08-02T09:23:38.000Z", 
    "sgv": 210, 
    "device": "share2", 
    "date": 1470129818000, 
    "_id": "57a0670e0b12fbe73f0c7956", 
    "type": "sgv"
  }, 
  {
    "direction": "Flat", 
    "trend": 4, 
    "dateString": "2016-08-02T09:18:37.000Z", 
    "sgv": 212, 
    "device": "share2", 
    "date": 1470129517000, 
    "_id": "57a065e20b12fbe73f0c7955", 
    "type": "sgv"
  }, 
  {
    "direction": "Flat", 
    "trend": 4, 
    "dateString": "2016-08-02T09:13:37.000Z", 
    "sgv": 214, 
    "device": "share2", 
    "date": 1470129217000, 
    "_id": "57a064b60b12fbe73f0c7954", 
    "type": "sgv"
  }, 
  {
    "direction": "Flat", 
    "trend": 4, 
    "dateString": "2016-08-02T09:08:38.000Z", 
    "sgv": 217, 
    "device": "share2", 
    "date": 1470128918000, 
    "_id": "57a0638a0b12fbe73f0c7953", 
    "type": "sgv"
  }, 
  {
    "direction": "Flat", 
    "trend": 4, 
    "dateString": "2016-08-02T09:03:37.000Z", 
    "sgv": 221, 
    "device": "share2", 
    "date": 1470128617000, 
    "_id": "57a0625e0b12fbe73f0c7952", 
    "type": "sgv"
  }, 
  {
    "direction": "Flat", 
    "trend": 4, 
    "dateString": "2016-08-02T08:58:36.000Z", 
    "sgv": 219, 
    "device": "share2", 
    "date": 1470128316000, 
    "_id": "57a061320b12fbe73f0c7951", 
    "type": "sgv"
  }, 
  {
    "direction": "Flat", 
    "trend": 4, 
    "dateString": "2016-08-02T08:53:36.000Z", 
    "sgv": 226, 
    "device": "share2", 
    "date": 1470128016000, 
    "_id": "57a060060b12fbe73f0c7950", 
    "type": "sgv"
  }
]