{
  "device": "openaps://openaps-lp", 
  "pump": {
    "battery": {
      "status": "normal", 
      "voltage": 1.4
    }, 
    "status": {
      "status": "normal", 
      "timestamp": "2016-08-02T07:40:50.000Z", 
      "bolusing": false, 
      "suspended": false
    }, 
    "reservoir": 41.3, 
    "clock": "2016-08-02T00:39:55"
  }, 
  "openaps": {
    "suggested": {
      "bg": 196, 
      "temp": "absolute", 
      "snoozeBG": 153, 
      "timestamp": "2016-08-02T07:41:21.000Z", 
      "rate": 0.7, 
      "reason": "Eventual BG 96<130, bolus snooze: eventual BG range 96-153; setting current basal of 0.7 as temp. Setting neutral temp basal of 0.7U/hr", 
      "eventualBG": 96, 
      "duration": 30, 
      "mealAssist": "Off: Carbs: undefined Boluses: undefined ISF: 80, Target: 130 Deviation: 8 BGI: -4.6", 
      "tick": -2
    }, 
    "iob": {
      "netbasalinsulin": 0.15, 
      "timestamp": "2016-08-02T07:41:20.000Z", 
      "activity": 0.0115, 
      "basaliob": 0.109, 
      "hightempinsulin": 0.15, 
      "bolussnooze": 0.473, 
      "iob": 1.353
    }, 
    "enacted": {
      "bg": 196, 
      "temp": "absolute", 
      "snoozeBG": 153, 
      "recieved": true, 
      "reason": "Eventual BG 96<130, bolus snooze: eventual BG range 96-153; setting current basal of 0.7 as temp. Setting neutral temp basal of 0.7U/hr", 
      "rate": 0.675, 
      "eventualBG": 96, 
      "timestamp": "2016-08-02T07:41:31.000Z", 
      "duration": 30, 
      "mealAssist": "Off: Carbs: undefined Boluses: undefined ISF: 80, Target: 130 Deviation: 8 BGI: -4.6", 
      "tick": -2
    }
  }
}