{
  "device": "openaps://openaps-lp", 
  "pump": {
    "battery": {
      "status": "normal", 
      "voltage": 1.33
    }, 
    "status": {
      "status": "normal", 
      "timestamp": "2016-07-07T07:06:49.000Z", 
      "bolusing": false, 
      "suspended": false
    }, 
    "reservoir": 48.375, 
    "clock": "2016-07-07T09:04:22"
  }, 
  "openaps": {
    "suggested": {
      "bg": 74, 
      "temp": "absolute", 
      "snoozeBG": 63, 
      "timestamp": "2016-07-07T07:06:23.000Z", 
      "reason": "BG 74<85, delta 6>0, temp 0.8 ~ req 0.8U/hr", 
      "eventualBG": 63, 
      "mealAssist": "Off: Carbs: undefined Boluses: undefined ISF: 80, Target: 125 Deviation: 15 BGI: -3.08", 
      "tick": "+6"
    }, 
    "iob": {
      "netbasalinsulin": 0, 
      "timestamp": "2016-07-07T07:06:21.000Z", 
      "activity": 0.0077, 
      "basaliob": 0, 
      "hightempinsulin": 0, 
      "bolussnooze": 0, 
      "iob": 0.331
    }, 
    "enacted": {
      "bg": 74, 
      "temp": "absolute", 
      "missing": [
        "duration", 
        "rate"
      ], 
      "timestamp": "2016-07-07T07:06:30.000Z", 
      "snoozeBG": 63, 
      "reason": "BG 74<85, delta 6>0, temp 0.8 ~ req 0.8U/hr", 
      "eventualBG": 63, 
      "error": "missing required input fields", 
      "input": {
        "bg": 74, 
        "temp": "absolute", 
        "snoozeBG": 63, 
        "reason": "BG 74<85, delta 6>0, temp 0.8 ~ req 0.8U/hr", 
        "eventualBG": 63, 
        "mealAssist": "Off: Carbs: undefined Boluses: undefined ISF: 80, Target: 125 Deviation: 15 BGI: -3.08", 
        "tick": "+6"
      }, 
      "mealAssist": "Off: Carbs: undefined Boluses: undefined ISF: 80, Target: 125 Deviation: 15 BGI: -3.08", 
      "tick": "+6"
    }
  }
}