[
  {
    "direction": "Flat", 
    "trend": 4, 
    "dateString": "2016-07-16T23:49:14-07:00", 
    "sgv": 228, 
    "date": 1468738154000, 
    "device": "share2", 
    "_id": "578b2aed0b12fbe73f0c487d", 
    "type": "sgv"
  }, 
  {
    "direction": "Flat", 
    "trend": 4, 
    "dateString": "2016-07-16T23:44:14-07:00", 
    "sgv": 238, 
    "date": 1468737854000, 
    "device": "share2", 
    "_id": "578b29c10b12fbe73f0c487c", 
    "type": "sgv"
  }, 
  {
    "direction": "Flat", 
    "trend": 4, 
    "dateString": "2016-07-16T23:39:17-07:00", 
    "sgv": 236, 
    "date": 1468737557000, 
    "device": "share2", 
    "_id": "578b28950b12fbe73f0c487b", 
    "type": "sgv"
  }, 
  {
    "direction": "Flat", 
    "trend": 4, 
    "dateString": "2016-07-16T23:34:18-07:00", 
    "sgv": 236, 
    "date": 1468737258000, 
    "device": "share2", 
    "_id": "578b27690b12fbe73f0c4879", 
    "type": "sgv"
  }, 
  {
    "direction": "Flat", 
    "trend": 4, 
    "dateString": "2016-07-16T23:29:15-07:00", 
    "sgv": 234, 
    "date": 1468736955000, 
    "device": "share2", 
    "_id": "578b263d0b12fbe73f0c4877", 
    "type": "sgv"
  }, 
  {
    "direction": "Flat", 
    "trend": 4, 
    "dateString": "2016-07-16T23:24:13-07:00", 
    "sgv": 233, 
    "date": 1468736653000, 
    "device": "share2", 
    "_id": "578b25110b12fbe73f0c4875", 
    "type": "sgv"
  }, 
  {
    "direction": "Flat", 
    "trend": 4, 
    "dateString": "2016-07-16T23:19:14-07:00", 
    "sgv": 235, 
    "date": 1468736354000, 
    "device": "share2", 
    "_id": "578b23e50b12fbe73f0c4874", 
    "type": "sgv"
  }, 
  {
    "direction": "FortyFiveUp", 
    "trend": 3, 
    "dateString": "2016-07-16T23:14:15-07:00", 
    "sgv": 234, 
    "date": 1468736055000, 
    "device": "share2", 
    "_id": "578b22b90b12fbe73f0c4873", 
    "type": "sgv"
  }, 
  {
    "direction": "FortyFiveUp", 
    "trend": 3, 
    "dateString": "2016-07-16T23:09:15-07:00", 
    "sgv": 231, 
    "date": 1468735755000, 
    "device": "share2", 
    "_id": "578b218d0b12fbe73f0c4872", 
    "type": "sgv"
  }, 
  {
    "direction": "SingleUp", 
    "trend": 2, 
    "dateString": "2016-07-16T23:04:16-07:00", 
    "sgv": 227, 
    "date": 1468735456000, 
    "device": "share2", 
    "_id": "578b20610b12fbe73f0c4871", 
    "type": "sgv"
  }, 
  {
    "direction": "SingleUp", 
    "trend": 2, 
    "dateString": "2016-07-16T22:59:17-07:00", 
    "sgv": 219, 
    "date": 1468735157000, 
    "device": "share2", 
    "_id": "578b1f350b12fbe73f0c4870", 
    "type": "sgv"
  }, 
  {
    "direction": "FortyFiveUp", 
    "trend": 3, 
    "dateString": "2016-07-16T22:54:14-07:00", 
    "sgv": 206, 
    "date": 1468734854000, 
    "device": "share2", 
    "_id": "578b1e090b12fbe73f0c486e", 
    "type": "sgv"
  }, 
  {
    "direction": "Flat", 
    "trend": 4, 
    "dateString": "2016-07-16T22:49:14-07:00", 
    "sgv": 188, 
    "date": 1468734554000, 
    "device": "share2", 
    "_id": "578b1cdd0b12fbe73f0c486c", 
    "type": "sgv"
  }, 
  {
    "direction": "Flat", 
    "trend": 4, 
    "dateString": "2016-07-16T22:44:14-07:00", 
    "sgv": 182, 
    "date": 1468734254000, 
    "device": "share2", 
    "_id": "578b1bb10b12fbe73f0c486b", 
    "type": "sgv"
  }, 
  {
    "direction": "Flat", 
    "trend": 4, 
    "dateString": "2016-07-16T22:39:14-07:00", 
    "sgv": 182, 
    "date": 1468733954000, 
    "device": "share2", 
    "_id": "578b1a850b12fbe73f0c486a", 
    "type": "sgv"
  }, 
  {
    "direction": "Flat", 
    "trend": 4, 
    "dateString": "2016-07-16T22:34:14-07:00", 
    "sgv": 182, 
    "date": 1468733654000, 
    "device": "share2", 
    "_id": "578b19590b12fbe73f0c4868", 
    "type": "sgv"
  }, 
  {
    "direction": "Flat", 
    "trend": 4, 
    "dateString": "2016-07-16T22:29:14-07:00", 
    "sgv": 184, 
    "date": 1468733354000, 
    "device": "share2", 
    "_id": "578b182d0b12fbe73f0c4866", 
    "type": "sgv"
  }, 
  {
    "direction": "Flat", 
    "trend": 4, 
    "dateString": "2016-07-16T22:24:13-07:00", 
    "sgv": 186, 
    "date": 1468733053000, 
    "device": "share2", 
    "_id": "578b17010b12fbe73f0c4864", 
    "type": "sgv"
  }, 
  {
    "direction": "Flat", 
    "trend": 4, 
    "dateString": "2016-07-16T22:19:15-07:00", 
    "sgv": 177, 
    "date": 1468732755000, 
    "device": "share2", 
    "_id": "578b15d50b12fbe73f0c4863", 
    "type": "sgv"
  }, 
  {
    "direction": "Flat", 
    "trend": 4, 
    "dateString": "2016-07-16T22:14:14-07:00", 
    "sgv": 179, 
    "date": 1468732454000, 
    "device": "share2", 
    "_id": "578b14a90b12fbe73f0c4861", 
    "type": "sgv"
  }, 
  {
    "direction": "Flat", 
    "trend": 4, 
    "dateString": "2016-07-16T22:09:17-07:00", 
    "sgv": 180, 
    "date": 1468732157000, 
    "device": "share2", 
    "_id": "578b137d0b12fbe73f0c485f", 
    "type": "sgv"
  }, 
  {
    "direction": "FortyFiveDown", 
    "trend": 5, 
    "dateString": "2016-07-16T22:04:18-07:00", 
    "sgv": 170, 
    "date": 1468731858000, 
    "device": "share2", 
    "_id": "578b12510b12fbe73f0c485d", 
    "type": "sgv"
  }, 
  {
    "direction": "FortyFiveDown", 
    "trend": 5, 
    "dateString": "2016-07-16T21:59:15-07:00", 
    "sgv": 174, 
    "date": 1468731555000, 
    "device": "share2", 
    "_id": "578b11250b12fbe73f0c485c", 
    "type": "sgv"
  }, 
  {
    "direction": "FortyFiveDown", 
    "trend": 5, 
    "dateString": "2016-07-16T21:54:15-07:00", 
    "sgv": 182, 
    "date": 1468731255000, 
    "device": "share2", 
    "_id": "578b0ff90b12fbe73f0c485b", 
    "type": "sgv"
  }, 
  {
    "direction": "Flat", 
    "trend": 4, 
    "dateString": "2016-07-16T21:44:13-07:00", 
    "sgv": 204, 
    "date": 1468730653000, 
    "device": "share2", 
    "_id": "578b0da10b12fbe73f0c485a", 
    "type": "sgv"
  }, 
  {
    "direction": "FortyFiveUp", 
    "trend": 3, 
    "dateString": "2016-07-16T21:39:13-07:00", 
    "sgv": 204, 
    "date": 1468730353000, 
    "device": "share2", 
    "_id": "578b0c750b12fbe73f0c4859", 
    "type": "sgv"
  }, 
  {
    "direction": "SingleUp", 
    "trend": 2, 
    "dateString": "2016-07-16T21:34:12-07:00", 
    "sgv": 200, 
    "date": 1468730052000, 
    "device": "share2", 
    "_id": "578b0b490b12fbe73f0c4858", 
    "type": "sgv"
  }, 
  {
    "direction": "SingleUp", 
    "trend": 2, 
    "dateString": "2016-07-16T21:29:12-07:00", 
    "sgv": 195, 
    "date": 1468729752000, 
    "device": "share2", 
    "_id": "578b0a1d0b12fbe73f0c4856", 
    "type": "sgv"
  }, 
  {
    "direction": "SingleUp", 
    "trend": 2, 
    "dateString": "2016-07-16T21:24:12-07:00", 
    "sgv": 187, 
    "date": 1468729452000, 
    "device": "share2", 
    "_id": "578b08f10b12fbe73f0c4854", 
    "type": "sgv"
  }, 
  {
    "direction": "FortyFiveUp", 
    "trend": 3, 
    "dateString": "2016-07-16T21:19:15-07:00", 
    "sgv": 169, 
    "date": 1468729155000, 
    "device": "share2", 
    "_id": "578b07c50b12fbe73f0c4853", 
    "type": "sgv"
  }, 
  {
    "direction": "Flat", 
    "trend": 4, 
    "dateString": "2016-07-16T21:09:16-07:00", 
    "sgv": 156, 
    "date": 1468728556000, 
    "device": "share2", 
    "_id": "578b056d0b12fbe73f0c4851", 
    "type": "sgv"
  }, 
  {
    "direction": "Flat", 
    "trend": 4, 
    "dateString": "2016-07-16T20:29:13-07:00", 
    "sgv": 163, 
    "date": 1468726153000, 
    "device": "share2", 
    "_id": "578afc0d0b12fbe73f0c4850", 
    "type": "sgv"
  }, 
  {
    "direction": "Flat", 
    "trend": 4, 
    "dateString": "2016-07-16T20:24:13-07:00", 
    "sgv": 161, 
    "date": 1468725853000, 
    "device": "share2", 
    "_id": "578afae10b12fbe73f0c484f", 
    "type": "sgv"
  }, 
  {
    "direction": "Flat", 
    "trend": 4, 
    "dateString": "2016-07-16T20:19:14-07:00", 
    "sgv": 161, 
    "date": 1468725554000, 
    "device": "share2", 
    "_id": "578af9b50b12fbe73f0c484e", 
    "type": "sgv"
  }, 
  {
    "direction": "Flat", 
    "trend": 4, 
    "dateString": "2016-07-16T20:09:14-07:00", 
    "sgv": 153, 
    "date": 1468724954000, 
    "device": "share2", 
    "_id": "578af75d0b12fbe73f0c484d", 
    "type": "sgv"
  }, 
  {
    "direction": "Flat", 
    "trend": 4, 
    "dateString": "2016-07-16T19:54:13-07:00", 
    "sgv": 141, 
    "date": 1468724053000, 
    "device": "share2", 
    "_id": "578af3d90b12fbe73f0c484c", 
    "type": "sgv"
  }, 
  {
    "direction": "Flat", 
    "trend": 4, 
    "dateString": "2016-07-16T19:49:13-07:00", 
    "sgv": 140, 
    "date": 1468723753000, 
    "device": "share2", 
    "_id": "578af2ad0b12fbe73f0c484b", 
    "type": "sgv"
  }, 
  {
    "direction": "FortyFiveUp", 
    "trend": 3, 
    "dateString": "2016-07-16T19:39:13-07:00", 
    "sgv": 154, 
    "date": 1468723153000, 
    "device": "share2", 
    "_id": "578af0550b12fbe73f0c484a", 
    "type": "sgv"
  }, 
  {
    "direction": "FortyFiveUp", 
    "trend": 3, 
    "dateString": "2016-07-16T19:34:13-07:00", 
    "sgv": 149, 
    "date": 1468722853000, 
    "device": "share2", 
    "_id": "578aef290b12fbe73f0c4849", 
    "type": "sgv"
  }, 
  {
    "direction": "FortyFiveUp", 
    "trend": 3, 
    "dateString": "2016-07-16T19:29:14-07:00", 
    "sgv": 142, 
    "date": 1468722554000, 
    "device": "share2", 
    "_id": "578aedfd0b12fbe73f0c4848", 
    "type": "sgv"
  }, 
  {
    "direction": "Flat", 
    "trend": 4, 
    "dateString": "2016-07-16T19:24:14-07:00", 
    "sgv": 132, 
    "date": 1468722254000, 
    "device": "share2", 
    "_id": "578aecd10b12fbe73f0c4847", 
    "type": "sgv"
  }, 
  {
    "direction": "Flat", 
    "trend": 4, 
    "dateString": "2016-07-16T19:19:13-07:00", 
    "sgv": 125, 
    "date": 1468721953000, 
    "device": "share2", 
    "_id": "578aeba50b12fbe73f0c4846", 
    "type": "sgv"
  }, 
  {
    "direction": "Flat", 
    "trend": 4, 
    "dateString": "2016-07-16T19:14:15-07:00", 
    "sgv": 121, 
    "date": 1468721655000, 
    "device": "share2", 
    "_id": "578aea790b12fbe73f0c4845", 
    "type": "sgv"
  }, 
  {
    "direction": "Flat", 
    "trend": 4, 
    "dateString": "2016-07-16T19:09:15-07:00", 
    "sgv": 120, 
    "date": 1468721355000, 
    "device": "share2", 
    "_id": "578ae94d0b12fbe73f0c4844", 
    "type": "sgv"
  }, 
  {
    "direction": "Flat", 
    "trend": 4, 
    "dateString": "2016-07-16T19:04:13-07:00", 
    "sgv": 121, 
    "date": 1468721053000, 
    "device": "share2", 
    "_id": "578ae8210b12fbe73f0c4843", 
    "type": "sgv"
  }, 
  {
    "direction": "Flat", 
    "trend": 4, 
    "dateString": "2016-07-16T18:59:13-07:00", 
    "sgv": 122, 
    "date": 1468720753000, 
    "device": "share2", 
    "_id": "578ae6f50b12fbe73f0c4842", 
    "type": "sgv"
  }, 
  {
    "direction": "Flat", 
    "trend": 4, 
    "dateString": "2016-07-16T18:54:14-07:00", 
    "sgv": 122, 
    "date": 1468720454000, 
    "device": "share2", 
    "_id": "578ae5c90b12fbe73f0c4841", 
    "type": "sgv"
  }, 
  {
    "direction": "Flat", 
    "trend": 4, 
    "dateString": "2016-07-16T18:49:15-07:00", 
    "sgv": 123, 
    "date": 1468720155000, 
    "device": "share2", 
    "_id": "578ae49c0b12fbe73f0c4840", 
    "type": "sgv"
  }, 
  {
    "direction": "Flat", 
    "trend": 4, 
    "dateString": "2016-07-16T18:44:14-07:00", 
    "sgv": 124, 
    "date": 1468719854000, 
    "device": "share2", 
    "_id": "578ae3700b12fbe73f0c483f", 
    "type": "sgv"
  }, 
  {
    "direction": "Flat", 
    "trend": 4, 
    "dateString": "2016-07-16T18:39:14-07:00", 
    "sgv": 122, 
    "date": 1468719554000, 
    "device": "share2", 
    "_id": "578ae2450b12fbe73f0c483e", 
    "type": "sgv"
  }
]