[
  {
    "direction": "NONE",
    "trend": 0,
    "dateString": "2016-07-14T09:14:20+02:00",
    "sgv": 178,
    "date": 1468480460000,
    "device": "share2",
    "_id": "57873c410b12fbe73f0c3dc0",
    "type": "sgv",
    "glucose": 178
  },
  {
    "direction": "NONE",
    "trend": 0,
    "dateString": "2016-07-14T09:09:20+02:00",
    "sgv": 167,
    "date": 1468480160000,
    "device": "share2",
    "_id": "57873b150b12fbe73f0c3dbe",
    "type": "sgv",
    "glucose": 167
  },
  {
    "direction": "NONE",
    "trend": 0,
    "dateString": "2016-07-14T09:04:19+02:00",
    "sgv": 145,
    "date": 1468479859000,
    "device": "share2",
    "_id": "578739e90b12fbe73f0c3dbd",
    "type": "sgv",
    "glucose": 145
  },
  {
    "direction": "NONE",
    "trend": 0,
    "dateString": "2016-07-14T08:54:20+02:00",
    "sgv": 88,
    "date": 1468479260000,
    "device": "share2",
    "_id": "578737910b12fbe73f0c3dbb",
    "type": "sgv",
    "glucose": 88
  },
  {
    "direction": "FortyFiveDown",
    "trend": 5,
    "dateString": "2016-07-14T08:19:20+02:00",
    "sgv": 117,
    "date": 1468477160000,
    "device": "share2",
    "_id": "57872f5d0b12fbe73f0c3dba",
    "type": "sgv",
    "glucose": 117
  },
  {
    "direction": "Flat",
    "trend": 4,
    "dateString": "2016-07-14T08:14:20+02:00",
    "sgv": 132,
    "date": 1468476860000,
    "device": "share2",
    "_id": "57872e310b12fbe73f0c3db8",
    "type": "sgv",
    "glucose": 132
  },
  {
    "direction": "Flat",
    "trend": 4,
    "dateString": "2016-07-14T08:09:19+02:00",
    "sgv": 137,
    "date": 1468476559000,
    "device": "share2",
    "_id": "57872d050b12fbe73f0c3db7",
    "type": "sgv",
    "glucose": 137
  },
  {
    "direction": "FortyFiveDown",
    "trend": 5,
    "dateString": "2016-07-14T07:44:22+02:00",
    "sgv": 144,
    "date": 1468475062000,
    "device": "share2",
    "_id": "578727290b12fbe73f0c3db5",
    "type": "sgv",
    "glucose": 144
  },
  {
    "direction": "FortyFiveDown",
    "trend": 5,
    "dateString": "2016-07-14T07:34:21+02:00",
    "sgv": 153,
    "date": 1468474461000,
    "device": "share2",
    "_id": "578724d10b12fbe73f0c3db4",
    "type": "sgv",
    "glucose": 153
  },
  {
    "direction": "FortyFiveDown",
    "trend": 5,
    "dateString": "2016-07-14T07:29:21+02:00",
    "sgv": 160,
    "date": 1468474161000,
    "device": "share2",
    "_id": "578723a50b12fbe73f0c3db3",
    "type": "sgv",
    "glucose": 160
  },
  {
    "direction": "Flat",
    "trend": 4,
    "dateString": "2016-07-14T07:24:21+02:00",
    "sgv": 169,
    "date": 1468473861000,
    "device": "share2",
    "_id": "578722790b12fbe73f0c3db1",
    "type": "sgv",
    "glucose": 169
  },
  {
    "direction": "Flat",
    "trend": 4,
    "dateString": "2016-07-14T07:19:21+02:00",
    "sgv": 171,
    "date": 1468473561000,
    "device": "share2",
    "_id": "5787214d0b12fbe73f0c3daf",
    "type": "sgv",
    "glucose": 171
  },
  {
    "direction": "Flat",
    "trend": 4,
    "dateString": "2016-07-14T07:14:20+02:00",
    "sgv": 179,
    "date": 1468473260000,
    "device": "share2",
    "_id": "578720210b12fbe73f0c3dae",
    "type": "sgv",
    "glucose": 179
  },
  {
    "direction": "Flat",
    "trend": 4,
    "dateString": "2016-07-14T07:09:20+02:00",
    "sgv": 181,
    "date": 1468472960000,
    "device": "share2",
    "_id": "57871ef50b12fbe73f0c3dad",
    "type": "sgv",
    "glucose": 181
  },
  {
    "direction": "FortyFiveDown",
    "trend": 5,
    "dateString": "2016-07-14T07:04:20+02:00",
    "sgv": 176,
    "date": 1468472660000,
    "device": "share2",
    "_id": "57871dc90b12fbe73f0c3dab",
    "type": "sgv",
    "glucose": 176
  },
  {
    "direction": "Flat",
    "trend": 4,
    "dateString": "2016-07-14T06:59:29+02:00",
    "sgv": 184,
    "date": 1468472369000,
    "device": "share2",
    "_id": "57871c9d0b12fbe73f0c3daa",
    "type": "sgv",
    "glucose": 184
  },
  {
    "direction": "Flat",
    "trend": 4,
    "dateString": "2016-07-14T06:54:21+02:00",
    "sgv": 191,
    "date": 1468472061000,
    "device": "share2",
    "_id": "57871b710b12fbe73f0c3da9",
    "type": "sgv",
    "glucose": 191
  },
  {
    "direction": "Flat",
    "trend": 4,
    "dateString": "2016-07-14T06:49:22+02:00",
    "sgv": 192,
    "date": 1468471762000,
    "device": "share2",
    "_id": "57871a450b12fbe73f0c3da8",
    "type": "sgv",
    "glucose": 192
  },
  {
    "direction": "Flat",
    "trend": 4,
    "dateString": "2016-07-14T06:44:21+02:00",
    "sgv": 191,
    "date": 1468471461000,
    "device": "share2",
    "_id": "578719190b12fbe73f0c3da6",
    "type": "sgv",
    "glucose": 191
  },
  {
    "direction": "Flat",
    "trend": 4,
    "dateString": "2016-07-14T06:39:21+02:00",
    "sgv": 193,
    "date": 1468471161000,
    "device": "share2",
    "_id": "578717ed0b12fbe73f0c3da5",
    "type": "sgv",
    "glucose": 193
  },
  {
    "direction": "Flat",
    "trend": 4,
    "dateString": "2016-07-14T06:34:21+02:00",
    "sgv": 195,
    "date": 1468470861000,
    "device": "share2",
    "_id": "578716c10b12fbe73f0c3da4",
    "type": "sgv",
    "glucose": 195
  },
  {
    "direction": "Flat",
    "trend": 4,
    "dateString": "2016-07-14T06:29:20+02:00",
    "sgv": 198,
    "date": 1468470560000,
    "device": "share2",
    "_id": "578715950b12fbe73f0c3da3",
    "type": "sgv",
    "glucose": 198
  },
  {
    "direction": "Flat",
    "trend": 4,
    "dateString": "2016-07-14T06:24:21+02:00",
    "sgv": 191,
    "date": 1468470261000,
    "device": "share2",
    "_id": "578714690b12fbe73f0c3da2",
    "type": "sgv",
    "glucose": 191
  },
  {
    "direction": "Flat",
    "trend": 4,
    "dateString": "2016-07-14T06:19:19+02:00",
    "sgv": 190,
    "date": 1468469959000,
    "device": "share2",
    "_id": "5787133d0b12fbe73f0c3da1",
    "type": "sgv",
    "glucose": 190
  },
  {
    "direction": "Flat",
    "trend": 4,
    "dateString": "2016-07-14T06:14:19+02:00",
    "sgv": 185,
    "date": 1468469659000,
    "device": "share2",
    "_id": "578712110b12fbe73f0c3d9f",
    "type": "sgv",
    "glucose": 185
  },
  {
    "direction": "Flat",
    "trend": 4,
    "dateString": "2016-07-14T06:09:26+02:00",
    "sgv": 186,
    "date": 1468469366000,
    "device": "share2",
    "_id": "578710e50b12fbe73f0c3d9e",
    "type": "sgv",
    "glucose": 186
  },
  {
    "direction": "Flat",
    "trend": 4,
    "dateString": "2016-07-14T06:04:22+02:00",
    "sgv": 186,
    "date": 1468469062000,
    "device": "share2",
    "_id": "57870fb90b12fbe73f0c3d9d",
    "type": "sgv",
    "glucose": 186
  },
  {
    "direction": "Flat",
    "trend": 4,
    "dateString": "2016-07-14T05:59:20+02:00",
    "sgv": 186,
    "date": 1468468760000,
    "device": "share2",
    "_id": "57870e8d0b12fbe73f0c3d9c",
    "type": "sgv",
    "glucose": 186
  },
  {
    "direction": "Flat",
    "trend": 4,
    "dateString": "2016-07-14T05:54:20+02:00",
    "sgv": 187,
    "date": 1468468460000,
    "device": "share2",
    "_id": "57870d610b12fbe73f0c3d9b",
    "type": "sgv",
    "glucose": 187
  },
  {
    "direction": "Flat",
    "trend": 4,
    "dateString": "2016-07-14T05:49:19+02:00",
    "sgv": 187,
    "date": 1468468159000,
    "device": "share2",
    "_id": "57870c350b12fbe73f0c3d9a",
    "type": "sgv",
    "glucose": 187
  },
  {
    "direction": "Flat",
    "trend": 4,
    "dateString": "2016-07-14T05:44:22+02:00",
    "sgv": 186,
    "date": 1468467862000,
    "device": "share2",
    "_id": "57870b090b12fbe73f0c3d98",
    "type": "sgv",
    "glucose": 186
  },
  {
    "direction": "Flat",
    "trend": 4,
    "dateString": "2016-07-14T05:39:22+02:00",
    "sgv": 185,
    "date": 1468467562000,
    "device": "share2",
    "_id": "578709dd0b12fbe73f0c3d97",
    "type": "sgv",
    "glucose": 185
  },
  {
    "direction": "Flat",
    "trend": 4,
    "dateString": "2016-07-14T05:34:20+02:00",
    "sgv": 184,
    "date": 1468467260000,
    "device": "share2",
    "_id": "578708b10b12fbe73f0c3d96",
    "type": "sgv",
    "glucose": 184
  },
  {
    "direction": "Flat",
    "trend": 4,
    "dateString": "2016-07-14T05:29:20+02:00",
    "sgv": 183,
    "date": 1468466960000,
    "device": "share2",
    "_id": "578707850b12fbe73f0c3d95",
    "type": "sgv",
    "glucose": 183
  },
  {
    "direction": "NONE",
    "trend": 0,
    "dateString": "2016-07-14T05:24:19+02:00",
    "sgv": 182,
    "date": 1468466659000,
    "device": "share2",
    "_id": "578706590b12fbe73f0c3d94",
    "type": "sgv",
    "glucose": 182
  },
  {
    "direction": "NONE",
    "trend": 0,
    "dateString": "2016-07-14T05:19:20+02:00",
    "sgv": 182,
    "date": 1468466360000,
    "device": "share2",
    "_id": "5787052d0b12fbe73f0c3d93",
    "type": "sgv",
    "glucose": 182
  },
  {
    "direction": "NONE",
    "trend": 0,
    "dateString": "2016-07-14T05:14:20+02:00",
    "sgv": 183,
    "date": 1468466060000,
    "device": "share2",
    "_id": "578704010b12fbe73f0c3d91",
    "type": "sgv",
    "glucose": 183
  },
  {
    "direction": "NONE",
    "trend": 0,
    "dateString": "2016-07-14T05:09:21+02:00",
    "sgv": 182,
    "date": 1468465761000,
    "device": "share2",
    "_id": "578702d50b12fbe73f0c3d90",
    "type": "sgv",
    "glucose": 182
  },
  {
    "direction": "NONE",
    "trend": 0,
    "dateString": "2016-07-14T05:04:21+02:00",
    "sgv": 181,
    "date": 1468465461000,
    "device": "share2",
    "_id": "578701a90b12fbe73f0c3d8e",
    "type": "sgv",
    "glucose": 181
  },
  {
    "direction": "NONE",
    "trend": 0,
    "dateString": "2016-07-14T04:59:20+02:00",
    "sgv": 181,
    "date": 1468465160000,
    "device": "share2",
    "_id": "5787007d0b12fbe73f0c3d8d",
    "type": "sgv",
    "glucose": 181
  },
  {
    "direction": "NONE",
    "trend": 0,
    "dateString": "2016-07-14T04:04:22+02:00",
    "sgv": 173,
    "date": 1468461862000,
    "device": "share2",
    "_id": "5786f3990b12fbe73f0c3d8b",
    "type": "sgv",
    "glucose": 173
  },
  {
    "direction": "NONE",
    "trend": 0,
    "dateString": "2016-07-14T03:59:21+02:00",
    "sgv": 194,
    "date": 1468461561000,
    "device": "share2",
    "_id": "5786f26d0b12fbe73f0c3d89",
    "type": "sgv",
    "glucose": 194
  },
  {
    "direction": "Flat",
    "trend": 4,
    "dateString": "2016-07-14T03:54:20+02:00",
    "sgv": 201,
    "date": 1468461260000,
    "device": "share2",
    "_id": "5786f1410b12fbe73f0c3d88",
    "type": "sgv",
    "glucose": 201
  },
  {
    "direction": "Flat",
    "trend": 4,
    "dateString": "2016-07-14T03:49:20+02:00",
    "sgv": 203,
    "date": 1468460960000,
    "device": "share2",
    "_id": "5786f0150b12fbe73f0c3d87",
    "type": "sgv",
    "glucose": 203
  },
  {
    "direction": "Flat",
    "trend": 4,
    "dateString": "2016-07-14T03:44:22+02:00",
    "sgv": 205,
    "date": 1468460662000,
    "device": "share2",
    "_id": "5786eee90b12fbe73f0c3d86",
    "type": "sgv",
    "glucose": 205
  },
  {
    "direction": "Flat",
    "trend": 4,
    "dateString": "2016-07-14T03:39:21+02:00",
    "sgv": 205,
    "date": 1468460361000,
    "device": "share2",
    "_id": "5786edbd0b12fbe73f0c3d84",
    "type": "sgv",
    "glucose": 205
  },
  {
    "direction": "Flat",
    "trend": 4,
    "dateString": "2016-07-14T03:34:20+02:00",
    "sgv": 206,
    "date": 1468460060000,
    "device": "share2",
    "_id": "5786ec910b12fbe73f0c3d83",
    "type": "sgv",
    "glucose": 206
  },
  {
    "direction": "Flat",
    "trend": 4,
    "dateString": "2016-07-14T03:29:21+02:00",
    "sgv": 210,
    "date": 1468459761000,
    "device": "share2",
    "_id": "5786eb650b12fbe73f0c3d82",
    "type": "sgv",
    "glucose": 210
  },
  {
    "direction": "NONE",
    "trend": 0,
    "dateString": "2016-07-14T03:24:20+02:00",
    "sgv": 210,
    "date": 1468459460000,
    "device": "share2",
    "_id": "5786ea390b12fbe73f0c3d81",
    "type": "sgv",
    "glucose": 210
  },
  {
    "direction": "NONE",
    "trend": 0,
    "dateString": "2016-07-14T03:19:21+02:00",
    "sgv": 210,
    "date": 1468459161000,
    "device": "share2",
    "_id": "5786e90d0b12fbe73f0c3d80",
    "type": "sgv",
    "glucose": 210
  }
]
